agent_mcp/__init__.py
agent_mcp/client.py
agent_mcp/helpers/__init__.py
agent_mcp/helpers/general.py
agent_mcp/servers/server.py
agents/__init__.py
agents/base.py
agents/builders.py
agents/react_agent.py
config/__init__.py
config/logging.py
config/mcp_config.py
config/workflow.py
loggers/__init__.py
loggers/base.py
model_providers/__init__.py
model_providers/base.py
model_providers/factory.py
model_providers/groq.py
model_providers/ollama.py
prompts/__init__.py
prompts/agent_prompts.py
tools/__init__.py
tools/abstractions.py
tools/base.py
tools/decorators.py
tools/general.py
reactive_agents-0.2.0.dist-info/LICENSE
reactive_agents-0.2.0.dist-info/METADATA
reactive_agents-0.2.0.dist-info/WHEEL
reactive_agents-0.2.0.dist-info/RECORD
