Metadata-Version: 2.3
Name: reactive-agents
Version: 0.2.0
Summary: A custom reactive AI Agent framework for LLM-driven task execution
License: MIT
Keywords: ai,agents,llm,automation,workflow
Author: Tyler Buell
Maintainer: Tyler Buell
Requires-Python: >=3.10,<4.0
Classifier: Development Status :: 4 - Beta
Classifier: Intended Audience :: Developers
Classifier: License :: OSI Approved :: MIT License
Classifier: Programming Language :: Python :: 3
Classifier: Programming Language :: Python :: 3.10
Classifier: Programming Language :: Python :: 3.11
Classifier: Programming Language :: Python :: 3.12
Classifier: Programming Language :: Python :: 3.13
Classifier: Topic :: Scientific/Engineering :: Artificial Intelligence
Classifier: Topic :: Software Development :: Libraries :: Python Modules
Requires-Dist: colorlog (>=6.9.0,<7.0.0)
Requires-Dist: docstring-parser (>=0.16,<0.17)
Requires-Dist: groq (>=0.13.0,<0.14.0)
Requires-Dist: markitdown (>=0.0.1a3,<0.0.2)
Requires-Dist: mcp (>=1.4.1,<2.0.0)
Requires-Dist: ollama (>=0.4.4,<0.5.0)
Requires-Dist: pydantic (>=2.10.3,<3.0.0)
Requires-Dist: python-dotenv (>=1.0.1,<2.0.0)
Requires-Dist: requests (>=2.32.3,<3.0.0)
Project-URL: Documentation, https://github.com/tylerbuell/reactive-ai-agent/blob/main/README.md
Project-URL: Homepage, https://github.com/tylerbuell/reactive-ai-agent
Project-URL: Repository, https://github.com/tylerbuell/reactive-ai-agent
